ATTools/ATTools.py
ATTools/__init__.py
ATTools-0.2.0.dist-info/METADATA
ATTools-0.2.0.dist-info/WHEEL
ATTools-0.2.0.dist-info/top_level.txt
ATTools-0.2.0.dist-info/RECORD
