Metadata-Version: 2.1
Name: ATTools
Version: 0.2.0
Project-URL: Documentation, https://github.com/BEWARETHEDEAD/ATTools/tree/main
Requires-Python: >=3.7
Requires-Dist: asyncio
Requires-Dist: aiohttp
Requires-Dist: tonconnect
Requires-Dist: dedust
Requires-Dist: xjet
Requires-Dist: tontools
Requires-Dist: tonsdk
